[
{
    "model": "accounts.baseuser",
    "pk": 1,
    "fields": {
        "password": "pbkdf2_sha256$180000$LcxqBdNCQ7oX$Ir3wQzJ9Q4/Y4YleNyThzGo+sskgGj76lcw+bwRFTlo=",
        "last_login": null,
        "email": "admin@admin.com",
        "created_at": "2021-01-27T13:07:25.225",
        "updated_at": "2021-01-27T13:07:25.225",
        "token_expired": 0,
        "is_active": true,
        "is_superuser": true,
        "is_staff": true,
        "groups": [],
        "user_permissions": []
    }
},
{
    "model": "accounts.baseuser",
    "pk": 2,
    "fields": {
        "password": "pbkdf2_sha256$180000$8mObeYJiTpf8$efFoY5IQOuNOicc7GSYPAS1jI+SDeiGVoTKB2xQ+yb0=",
        "last_login": null,
        "email": "doctor1@doctor.com",
        "created_at": "2021-01-27T13:09:58.484",
        "updated_at": "2021-01-27T13:09:58.484",
        "token_expired": 0,
        "is_active": true,
        "is_superuser": false,
        "is_staff": false,
        "groups": [
            1
        ],
        "user_permissions": [
            25,
            26,
            27,
            28
        ]
    }
},
{
    "model": "accounts.baseuser",
    "pk": 3,
    "fields": {
        "password": "pbkdf2_sha256$180000$2fVbmyndKE6g$0P1UYnqXsaVQu5QCWnbYZfywNGLObZrc6gh9opUyMPg=",
        "last_login": null,
        "email": "doctor2@doctor.com",
        "created_at": "2021-01-27T13:10:12.729",
        "updated_at": "2021-01-27T13:10:12.729",
        "token_expired": 0,
        "is_active": true,
        "is_superuser": false,
        "is_staff": false,
        "groups": [
            1
        ],
        "user_permissions": [
            25,
            26,
            27,
            28
        ]
    }
},
{
    "model": "accounts.baseuser",
    "pk": 4,
    "fields": {
        "password": "pbkdf2_sha256$180000$ZU6j4SVyqwva$L32w6exMZn2X6tzO3c6V6wR6dr5AYoe1Gxt3PDjXbiY=",
        "last_login": null,
        "email": "doctor3@doctor.com",
        "created_at": "2021-01-27T13:10:28.780",
        "updated_at": "2021-01-27T13:10:28.780",
        "token_expired": 0,
        "is_active": true,
        "is_superuser": false,
        "is_staff": false,
        "groups": [
            1
        ],
        "user_permissions": [
            25,
            26,
            27,
            28
        ]
    }
},
{
    "model": "accounts.baseuser",
    "pk": 5,
    "fields": {
        "password": "pbkdf2_sha256$180000$wVMfPQnAiwHE$yOc96Voqqr4X9LAlzSuYdEUtsX8RxpZw6qd06eGATqw=",
        "last_login": "2021-01-27T15:15:14.894",
        "email": "patient1@patient.com",
        "created_at": "2021-01-27T13:12:08.547",
        "updated_at": "2021-01-27T13:12:08.547",
        "token_expired": 0,
        "is_active": true,
        "is_superuser": false,
        "is_staff": false,
        "groups": [
            2
        ],
        "user_permissions": [
            29,
            30,
            31,
            32
        ]
    }
},
{
    "model": "accounts.baseuser",
    "pk": 6,
    "fields": {
        "password": "pbkdf2_sha256$180000$ngJ6Wf8TqZ90$Xvt5AEyuJQ2csfuWfW9SwjhHADRSPL5yhmO+bBZecA0=",
        "last_login": null,
        "email": "patient2@patient.com",
        "created_at": "2021-01-27T13:12:24.331",
        "updated_at": "2021-01-27T13:12:24.331",
        "token_expired": 0,
        "is_active": true,
        "is_superuser": false,
        "is_staff": false,
        "groups": [
            2
        ],
        "user_permissions": [
            29,
            30,
            31,
            32
        ]
    }
},
{
    "model": "accounts.baseuser",
    "pk": 7,
    "fields": {
        "password": "pbkdf2_sha256$180000$fX9C2goakfvC$kxE02oHedECX06hrgYL6UaaoU17GPtIZf9OuyZcnYv8=",
        "last_login": null,
        "email": "patient3@patient.com",
        "created_at": "2021-01-27T13:15:28.470",
        "updated_at": "2021-01-27T13:15:28.470",
        "token_expired": 0,
        "is_active": true,
        "is_superuser": false,
        "is_staff": false,
        "groups": [],
        "user_permissions": []
    }
},
{
    "model": "accounts.baseuser",
    "pk": 8,
    "fields": {
        "password": "pbkdf2_sha256$180000$LxKegaf96sSl$MQ+MRNPLhqUQpmVGKF6ym8SlPX7Dodr4dus5lY3q5Kw=",
        "last_login": null,
        "email": "patient4@patient.com",
        "created_at": "2021-01-27T13:15:44.743",
        "updated_at": "2021-01-27T13:15:44.743",
        "token_expired": 0,
        "is_active": true,
        "is_superuser": false,
        "is_staff": false,
        "groups": [],
        "user_permissions": []
    }
},
{
    "model": "accounts.doctor",
    "pk": 2,
    "fields": {
        "first_name": "\uc758\uc0ac",
        "last_name": "\uc77c",
        "gender": "MALE",
        "address": "\uc11c\uc6b8\ud2b9\ubcc4\uc2dc",
        "phone": "010-1111-1111",
        "created_at": "2021-01-27T13:09:58.512",
        "updated_at": "2021-01-27T13:09:58.512",
        "major": 1,
        "description": "\uccab \ubc88\uc9f8 \uc758\uc0ac"
    }
},
{
    "model": "accounts.doctor",
    "pk": 3,
    "fields": {
        "first_name": "\uc758\uc0ac",
        "last_name": "\uc774",
        "gender": "MALE",
        "address": "\uc11c\uc6b8\ud2b9\ubcc4\uc2dc",
        "phone": "010-1111-1112",
        "created_at": "2021-01-27T13:10:12.745",
        "updated_at": "2021-01-27T13:10:12.745",
        "major": 1,
        "description": "\ub450 \ubc88\uc9f8 \uc758\uc0ac"
    }
},
{
    "model": "accounts.doctor",
    "pk": 4,
    "fields": {
        "first_name": "\uc758\uc0ac",
        "last_name": "\uc0bc",
        "gender": "MALE",
        "address": "\uc11c\uc6b8\ud2b9\ubcc4\uc2dc",
        "phone": "010-1111-1113",
        "created_at": "2021-01-27T13:10:28.794",
        "updated_at": "2021-01-27T13:10:28.794",
        "major": 1,
        "description": "\uc138 \ubc88\uc9f8 \uc758\uc0ac"
    }
},
{
    "model": "accounts.patient",
    "pk": 5,
    "fields": {
        "first_name": "\ud658\uc790",
        "last_name": "\uc77c",
        "gender": "MALE",
        "address": "\uc11c\uc6b8\uc5b4\ub518\uac00",
        "phone": "010-2222-1111",
        "created_at": "2021-01-27T13:12:08.560",
        "updated_at": "2021-01-27T13:12:08.560",
        "doctor": 2,
        "age": 33,
        "emergency_call": "02-119"
    }
},
{
    "model": "accounts.patient",
    "pk": 6,
    "fields": {
        "first_name": "\ud658\uc790",
        "last_name": "\uc77c",
        "gender": "MALE",
        "address": "\uc11c\uc6b8\uc5b4\ub518\uac00",
        "phone": "010-2222-1112",
        "created_at": "2021-01-27T13:12:24.349",
        "updated_at": "2021-01-27T13:12:24.349",
        "doctor": 2,
        "age": 33,
        "emergency_call": "02-119"
    }
},
{
    "model": "accounts.patient",
    "pk": 7,
    "fields": {
        "first_name": "\ud658\uc790",
        "last_name": "\uc0bc",
        "gender": "MALE",
        "address": "\uc11c\uc6b8\uc5b4\ub518\uac00",
        "phone": "010-2222-1113",
        "created_at": "2021-01-27T13:15:28.501",
        "updated_at": "2021-01-27T13:15:28.501",
        "doctor": 3,
        "age": 33,
        "emergency_call": "02-119"
    }
},
{
    "model": "accounts.patient",
    "pk": 8,
    "fields": {
        "first_name": "\ud658\uc790",
        "last_name": "\uc0ac",
        "gender": "MALE",
        "address": "\uc11c\uc6b8\uc5b4\ub518\uac00",
        "phone": "010-2222-1114",
        "created_at": "2021-01-27T13:15:44.759",
        "updated_at": "2021-01-27T13:15:44.759",
        "doctor": 3,
        "age": 33,
        "emergency_call": "02-119"
    }
}
]
